odoo/addons/sale_project_timesheet_by_seniority/README.rst
odoo/addons/sale_project_timesheet_by_seniority/__init__.py
odoo/addons/sale_project_timesheet_by_seniority/__manifest__.py
odoo/addons/sale_project_timesheet_by_seniority/i18n/fr.po
odoo/addons/sale_project_timesheet_by_seniority/i18n/it.po
odoo/addons/sale_project_timesheet_by_seniority/i18n/sale_project_timesheet_by_seniority.pot
odoo/addons/sale_project_timesheet_by_seniority/models/__init__.py
odoo/addons/sale_project_timesheet_by_seniority/models/account_analytic_line.py
odoo/addons/sale_project_timesheet_by_seniority/models/hr_employee.py
odoo/addons/sale_project_timesheet_by_seniority/models/hr_employee_seniority_level.py
odoo/addons/sale_project_timesheet_by_seniority/models/product_template.py
odoo/addons/sale_project_timesheet_by_seniority/models/sale.py
odoo/addons/sale_project_timesheet_by_seniority/readme/CONFIGURE.rst
odoo/addons/sale_project_timesheet_by_seniority/readme/CONTRIBUTORS.rst
odoo/addons/sale_project_timesheet_by_seniority/readme/DESCRIPTION.rst
odoo/addons/sale_project_timesheet_by_seniority/readme/USAGE.rst
odoo/addons/sale_project_timesheet_by_seniority/security/ir.model.access.csv
odoo/addons/sale_project_timesheet_by_seniority/static/description/icon.png
odoo/addons/sale_project_timesheet_by_seniority/static/description/index.html
odoo/addons/sale_project_timesheet_by_seniority/tests/__init__.py
odoo/addons/sale_project_timesheet_by_seniority/tests/test_sale_project_timesheet_by_seniority.py
odoo/addons/sale_project_timesheet_by_seniority/views/hr_employee_seniority_level.xml
odoo12_addon_sale_project_timesheet_by_seniority-12.0.1.0.0.99.dev10.dist-info/METADATA
odoo12_addon_sale_project_timesheet_by_seniority-12.0.1.0.0.99.dev10.dist-info/WHEEL
odoo12_addon_sale_project_timesheet_by_seniority-12.0.1.0.0.99.dev10.dist-info/top_level.txt
odoo12_addon_sale_project_timesheet_by_seniority-12.0.1.0.0.99.dev10.dist-info/RECORD
